plexflow/__init__.py
plexflow/__main__.py
plexflow/core/.DS_Store
plexflow/core/__init__.py
plexflow/core/__pycache__/__init__.cpython-311.pyc
plexflow/core/__pycache__/__init__.cpython-312.pyc
plexflow/core/context/__init__.py
plexflow/core/context/__pycache__/__init__.cpython-311.pyc
plexflow/core/context/__pycache__/__init__.cpython-312.pyc
plexflow/core/context/__pycache__/context.cpython-311.pyc
plexflow/core/context/__pycache__/partial_context.cpython-311.pyc
plexflow/core/context/__pycache__/partial_context.cpython-312.pyc
plexflow/core/context/__pycache__/plexflow_context.cpython-311.pyc
plexflow/core/context/__pycache__/plexflow_property.cpython-311.pyc
plexflow/core/context/metadata/__init__.py
plexflow/core/context/metadata/__pycache__/__init__.cpython-311.pyc
plexflow/core/context/metadata/__pycache__/context.cpython-311.pyc
plexflow/core/context/metadata/context.py
plexflow/core/context/metadata/tmdb/__init__.py
plexflow/core/context/metadata/tmdb/__pycache__/context.cpython-311.pyc
plexflow/core/context/metadata/tmdb/context.py
plexflow/core/context/partial_context.py
plexflow/core/context/partials/__init__.py
plexflow/core/context/partials/__pycache__/__init__.cpython-311.pyc
plexflow/core/context/partials/__pycache__/__init__.cpython-312.pyc
plexflow/core/context/partials/__pycache__/cache.cpython-312.pyc
plexflow/core/context/partials/__pycache__/candidates.cpython-312.pyc
plexflow/core/context/partials/__pycache__/completed_downloads.cpython-312.pyc
plexflow/core/context/partials/__pycache__/context.cpython-312.pyc
plexflow/core/context/partials/__pycache__/ids.cpython-311.pyc
plexflow/core/context/partials/__pycache__/ids.cpython-312.pyc
plexflow/core/context/partials/__pycache__/movie.cpython-312.pyc
plexflow/core/context/partials/__pycache__/movie_assets.cpython-312.pyc
plexflow/core/context/partials/__pycache__/reports.cpython-312.pyc
plexflow/core/context/partials/__pycache__/show.cpython-312.pyc
plexflow-0.0.176.dist-info/METADATA
plexflow-0.0.176.dist-info/WHEEL
plexflow-0.0.176.dist-info/entry_points.txt
plexflow-0.0.176.dist-info/RECORD
