Metadata-Version: 2.3
Name: plexflow
Version: 0.0.176
Summary: A short description of the package.
License: MIT
Author: Your Name
Author-email: you@example.com
Requires-Python: >=3.12,<3.13
Classifier: Development Status :: 5 - Production/Stable
Classifier: Intended Audience :: Developers
Classifier: License :: OSI Approved :: MIT License
Classifier: Programming Language :: Python :: 3
Classifier: Programming Language :: Python :: 3.12
Classifier: Programming Language :: Python :: 3.10
Requires-Dist: apache-airflow (>=3.1.5,<4.0.0)
Requires-Dist: apache-airflow-providers-celery (>=3.10.0)
Requires-Dist: apache-airflow-providers-cncf-kubernetes (>=8.3.3,<9.0.0)
Requires-Dist: apache-airflow-providers-fab (>=1.5.0)
Requires-Dist: apache-airflow-providers-postgres (>=5.10.2,<6.0.0)
Requires-Dist: apache-airflow-providers-redis (>=3.7.0,<4.0.0)
Requires-Dist: apache-airflow-providers-standard (>=1.0.0)
Requires-Dist: arrow (>=1.3.0,<2.0.0)
Requires-Dist: asyncpg (>=0.30.0,<0.31.0)
Requires-Dist: avro (>=1.11.3,<2.0.0)
Requires-Dist: beautifulsoup4 (>=4.12.3,<5.0.0)
Requires-Dist: bitmath (>=1.3.3.1,<2.0.0.0)
Requires-Dist: brotli (>=1.1.0,<2.0.0)
Requires-Dist: cloudinary (>=1.41.0,<2.0.0)
Requires-Dist: cloudscraper (>=1.2.71,<2.0.0)
Requires-Dist: dataclasses-json (>=0.6.4,<0.7.0)
Requires-Dist: dateparser (>=1.2.0,<2.0.0)
Requires-Dist: duckduckgo-search (>=8.1.1,<9.0.0)
Requires-Dist: fake-useragent (>=1.4.0,<2.0.0)
Requires-Dist: faster-whisper (>=1.2.1,<2.0.0)
Requires-Dist: google-cloud-pubsub (>=2.28.0,<3.0.0)
Requires-Dist: google-genai (>=1.26.0,<2.0.0)
Requires-Dist: groq (>=1.0.0,<2.0.0)
Requires-Dist: html5lib (>=1.1,<2.0)
Requires-Dist: humanfriendly (>=10.0,<11.0)
Requires-Dist: iso639-lang (>=2.2.3,<3.0.0)
Requires-Dist: json-repair (>=0.19.1,<0.20.0)
Requires-Dist: kafka (>=1.3.5,<2.0.0)
Requires-Dist: langcodes (>=3.4.0,<4.0.0)
Requires-Dist: langdetect (>=1.0.9,<2.0.0)
Requires-Dist: lxml (>=5.1.0,<6.0.0)
Requires-Dist: mistralai (>=1.2.5,<2.0.0)
Requires-Dist: nodriver (>=0.48.1,<0.49.0)
Requires-Dist: numpy (==1.26.4)
Requires-Dist: opensubtitlescom (>=0.1.5,<0.2.0)
Requires-Dist: parse-torrent-title (>=2.8.1,<3.0.0)
Requires-Dist: pika (>=1.3.2,<2.0.0)
Requires-Dist: playwright (>=1.41.2,<2.0.0)
Requires-Dist: playwright-stealth (>=1.0.6,<2.0.0)
Requires-Dist: plexapi (==4.15.9)
Requires-Dist: psycopg2-binary (>=2.9.9,<3.0.0)
Requires-Dist: pyautogui (>=0.9.54,<0.10.0)
Requires-Dist: pydantic (>=2.6.1,<3.0.0)
Requires-Dist: pysrt (>=1.1.2,<2.0.0)
Requires-Dist: pytelegrambotapi (>=4.29.1,<5.0.0)
Requires-Dist: python-ffmpeg (>=2.0.10,<3.0.0)
Requires-Dist: python-ulid (>=2.7.0,<3.0.0)
Requires-Dist: qbittorrent-api (>=2025.2.0,<2026.0.0)
Requires-Dist: ratelimit (>=2.2.1,<3.0.0)
Requires-Dist: redis (>=4.1.3,<5.0.0)
Requires-Dist: requests (>=2.25.1,<3.0.0)
Requires-Dist: retrying (>=1.3.4,<2.0.0)
Requires-Dist: scrapy (>=2.11.2,<3.0.0)
Requires-Dist: seleniumbase (>=4.28.4,<5.0.0)
Requires-Dist: stable-ts (>=2.19.1,<3.0.0)
Requires-Dist: tmdbsimple (>=2.9.1,<3.0.0)
Requires-Dist: torch (>=2.2.0)
Requires-Dist: torchaudio (>=2.2.0)
Requires-Dist: tpblite (>=0.8.0,<0.9.0)
Requires-Dist: tqdm (>=4.67.1,<5.0.0)
Requires-Dist: transformers (>=4.57.3,<5.0.0)
Requires-Dist: tvdb-v4-official (>=1.1.0,<2.0.0)
Requires-Dist: tvdbsimple (>=1.0.6,<2.0.0)
Requires-Dist: uvicorn (>=0.40.0,<0.41.0)
Requires-Dist: webdriver-manager (>=4.0.2,<5.0.0)
Requires-Dist: wget (>=3.2,<4.0)
Requires-Dist: yt-dlp (>=2025.12.8,<2026.0.0)
